COPYING
MANIFEST.in
README.rst
mk-interesting-graphs.sh
setup.cfg
setup.py
contrib/policykit_auth_admin_keep/org.freedesktop.policykit.pkexec.run-plainbox-job.policy
contrib/policykit_yes/org.freedesktop.policykit.pkexec.run-plainbox-job.policy
docs/changelog.rst
docs/conf.py
docs/glossary.rst
docs/index.rst
docs/install.rst
docs/usage.rst
docs/_theme/plainbox/page.html
docs/_theme/plainbox/theme.conf
docs/appdev/index.rst
docs/author/faq.rst
docs/author/index.rst
docs/author/intro.rst
docs/author/provider-files.rst
docs/author/provider-i18n.rst
docs/author/provider-namespaces.rst
docs/author/provider-template.rst
docs/author/providers.rst
docs/author/qml-job-tutorial.rst
docs/author/rfc822.rst
docs/author/tutorial.rst
docs/author/whitelists.rst
docs/dev/architecture.rst
docs/dev/config.rst
docs/dev/index.rst
docs/dev/intro.rst
docs/dev/old.rst
docs/dev/resources.rst
docs/dev/trusted-launcher.rst
docs/manpages/CHECKBOX_DATA.rst
docs/manpages/CHECKBOX_SHARE.rst
docs/manpages/PLAINBOX_PROVIDER_DATA.rst
docs/manpages/PLAINBOX_SESSION_SHARE.rst
docs/manpages/index.rst
docs/manpages/plainbox-category-units.rst
docs/manpages/plainbox-check-config.rst
docs/manpages/plainbox-dev-analyze.rst
docs/manpages/plainbox-dev-crash.rst
docs/manpages/plainbox-dev-list.rst
docs/manpages/plainbox-dev-logtest.rst
docs/manpages/plainbox-dev-parse.rst
docs/manpages/plainbox-dev-script.rst
docs/manpages/plainbox-dev-special.rst
docs/manpages/plainbox-dev.rst
docs/manpages/plainbox-device.rst
docs/manpages/plainbox-exporter-units.rst
docs/manpages/plainbox-file-units.rst
docs/manpages/plainbox-job-units.rst
docs/manpages/plainbox-manage.py.rst
docs/manpages/plainbox-manifest-entry-units.rst
docs/manpages/plainbox-packaging-meta-data-units.rst
docs/manpages/plainbox-qml-shell.rst
docs/manpages/plainbox-run.rst
docs/manpages/plainbox-self-test.rst
docs/manpages/plainbox-session-archive.rst
docs/manpages/plainbox-session-export.rst
docs/manpages/plainbox-session-list.rst
plainbox.egg-info/PKG-INFO
plainbox.egg-info/SOURCES.txt
plainbox.egg-info/dependency_links.txt
plainbox.egg-info/entry_points.txt
plainbox.egg-info/requires.txt
plainbox.egg-info/top_level.txt
